CHANGES.txt
MANIFEST.in
README.txt
setup.py
slapos/__init__.py
slapos/zcbworkarounds.py
slapos.zcbworkarounds.egg-info/PKG-INFO
slapos.zcbworkarounds.egg-info/SOURCES.txt
slapos.zcbworkarounds.egg-info/dependency_links.txt
slapos.zcbworkarounds.egg-info/entry_points.txt
slapos.zcbworkarounds.egg-info/top_level.txt
slapos.zcbworkarounds.egg-info/zip-safe