Metadata-Version: 1.0
Name: slapos.zcbworkarounds
Version: 0.1
Summary: A zc.buildout extensions to workaround zc.buildout issues which are impacting ERP5 Appliance
Home-page: UNKNOWN
Author: UNKNOWN
Author-email: UNKNOWN
License: GPLv3
Platform: UNKNOWN
Classifier: Programming Language :: Python
Classifier: Framework :: Buildout :: Extension
Classifier: Topic :: Software Development :: Libraries :: Python Modules
